summdata/SummaryContinuous.py
summdata/SummaryStatistics.py
summdata/__init__.py
summdata/example.py
summdata-0.1.1.dist-info/METADATA
summdata-0.1.1.dist-info/WHEEL
summdata-0.1.1.dist-info/top_level.txt
summdata-0.1.1.dist-info/RECORD
