Metadata-Version: 2.1
Name: summdata
Version: 0.1.1
Summary: Python Summary Statistics
Author: Isabelle Vea
Author-email: isabelle.vea@gmail.com
